verilog-dump/gray_code_counter/gray_code_counter.v
module grey_code_counter_TEST();
   reg clk;
   wire [2:0] count;

   grey_code_counter Counter(clk, count);

   initial begin
	  $dumpvars;
	  
	  $display(" clk | count ");
	  $monitor(" %b | %b ", clk, count);
	  
	  clk = 0;
	  #100
		repeat (20) begin
		   #10 clk <= ~clk;
		end
   end
endmodule // u_test

module grey_code_counter(clk, count);
   input clk; // Input clock line
   output [2:0] count;

   wire 		clk;
   reg [2:0] 	i_count; // Internal count register 	
   reg [2:0] 	count;   // what the outside world sees

   initial
	 begin
		count <= 3'b000;
	 end

   always @ (posedge clk)
	 begin
		case (count)
		  3'b000: count = 3'b001;
		  3'b001: count = 3'b011;
		  3'b010: count = 3'b110;
		  3'b011: count = 3'b010;
		  3'b100: count = 3'b000;
		  3'b101: count = 3'b100;
		  3'b110: count = 3'b111;
		  3'b111: count = 3'b101;
		  default: count = 3'bxxx;
		endcase // case (count)
	 end // always @ (posedge clk)
   
endmodule // grey_code_counter

verilog-dump/gray_code_counter/dump.vcd
$date
	Mon Nov 14 20:42:47 2011
$end
$version
	Icarus Verilog
$end
$timescale
	1s
$end
$scope module grey_code_counter_TEST $end
$var wire 3 ! count [2:0] $end
$var reg 1 " clk $end
$scope module Counter $end
$var wire 1 # clk $end
$var reg 3 $ count [2:0] $end
$upscope $end
$upscope $end
$enddefinitions $end
#0
$dumpvars
b0 $
0#
0"
b0 !
$end
#110
b1 $
b1 !
1"
1#
#120
0"
0#
#130
b11 $
b11 !
1"
1#
#140
0"
0#
#150
b10 $
b10 !
1"
1#
#160
0"
0#
#170
b110 $
b110 !
1"
1#
#180
0"
0#
#190
b111 $
b111 !
1"
1#
#200
0"
0#
#210
b101 $
b101 !
1"
1#
#220
0"
0#
#230
b100 $
b100 !
1"
1#
#240
0"
0#
#250
b0 $
b0 !
1"
1#
#260
0"
0#
#270
b1 $
b1 !
1"
1#
#280
0"
0#
#290
b11 $
b11 !
1"
1#
